{
  "bancoDeListaDados": [
    {
      "listaNomes": "edd",
      "listaProfissao": "dev",
      "listaCpf": "223.231.313-13",
      "listaEmail": "dev@gmail.com",
      "listaNascimento": "3111-12-23T03:00:00.000Z",
      "listaCep": "23.333-333",
      "listaCelular": "(99) 93939-3231",
      "formularioTipo": "Apartamento",
      "formularioRenda": 10000,
      "formularioValor": 100000,
      "formularioValorEntrada": 20000,
      "formularioQtdParcela": 36,
      "operacaoFinanciamentoTotal": 80000,
      "dataDeSimulacao": "2021-11-29T02:46:51.767Z",
      "id": 1
    },
    {
      "listaNomes": "ednavan",
      "listaProfissao": "dev",
      "listaCpf": "228.311.111-11",
      "listaEmail": "ed@gmail.com",
      "listaNascimento": "1997-09-27T03:00:00.000Z",
      "listaCep": "29.333-488",
      "listaCelular": "(28) 34882-3322",
      "formularioTipo": "Bangalô",
      "formularioRenda": 10000,
      "formularioValor": 100000,
      "formularioValorEntrada": 20000,
      "formularioQtdParcela": 36,
      "operacaoFinanciamentoTotal": 80000,
      "valorTotalJuros": 2888.8888888888887,
      "dataDeSimulacao": "2021-11-29T12:47:47.908Z",
      "id": 2
    }
  ],
  "tiposImoveis": [
    "Kitnet",
    "Flat",
    "Apartamento",
    "Edícula",
    "Sobrado",
    "Bangalô",
    "Casa Geminada"
  ]
}